satvu/__init__.py
satvu/auth.py
satvu/auth_test.py
satvu/core.py
satvu/core_retry_test.py
satvu/core_streaming_test.py
satvu/core_test.py
satvu/py.typed
satvu/result.py
satvu/result_test.py
satvu/sdk.py
satvu/sdk_test.py
satvu/http/__init__.py
satvu/http/errors.py
satvu/http/errors_test.py
satvu/http/httpx_adapter.py
satvu/http/httpx_adapter_test.py
satvu/http/protocol.py
satvu/http/requests_adapter.py
satvu/http/requests_adapter_test.py
satvu/http/stdlib_adapter.py
satvu/http/stdlib_adapter_test.py
satvu/http/urllib3_adapter.py
satvu/http/urllib3_adapter_test.py
satvu/services/conftest.py
satvu/services/catalog/__init__.py
satvu/services/catalog/api.py
satvu/services/catalog/api_test.py
satvu/services/catalog/test_schemas.py
satvu/services/catalog/models/__init__.py
satvu/services/catalog/models/and_or_expression.py
satvu/services/catalog/models/and_or_expression_op.py
satvu/services/catalog/models/api_error.py
satvu/services/catalog/models/arithmetic_expression.py
satvu/services/catalog/models/arithmetic_expression_op.py
satvu/services/catalog/models/asset.py
satvu/services/catalog/models/asset_bands.py
satvu/services/catalog/models/asset_bands_nodata_type_1.py
satvu/services/catalog/models/asset_bands_statistics.py
satvu/services/catalog/models/bbox_literal.py
satvu/services/catalog/models/binary_comparison_predicate.py
satvu/services/catalog/models/binary_comparison_predicate_op.py
satvu/services/catalog/models/catalog.py
satvu/services/catalog/models/collection.py
satvu/services/catalog/models/collections.py
satvu/services/catalog/models/conformance.py
satvu/services/catalog/models/conformance_response_429.py
satvu/services/catalog/models/cql_2_queryables_schema.py
satvu/services/catalog/models/data_type_of_the_band.py
satvu/services/catalog/models/date_instant.py
satvu/services/catalog/models/error.py
satvu/services/catalog/models/extent.py
satvu/services/catalog/models/feature.py
satvu/services/catalog/models/feature_collection.py
satvu-0.3.1.dist-info/METADATA
satvu-0.3.1.dist-info/WHEEL
satvu-0.3.1.dist-info/licenses/LICENSE
satvu-0.3.1.dist-info/RECORD
