Metadata-Version: 2.4
Name: satvu
Version: 0.3.1
Summary: SatVu API SDK
Project-URL: Homepage, https://www.satellitevu.com/
Project-URL: Documentation, https://github.com/SatelliteVu/satvu-api-sdk#readme
Project-URL: Repository, https://github.com/SatelliteVu/satvu-api-sdk
Project-URL: Issues, https://github.com/SatelliteVu/satvu-api-sdk/issues
Project-URL: Changelog, https://github.com/SatelliteVu/satvu-api-sdk/blob/main/CHANGELOG.md
Author-email: Christian Wygoda <christian.wygoda@satellitevu.com>, James Harrison <james.harrison@satellitevu.com>, Zhelini Raveendran <zhelini.raveendran@satellitevu.com>
License-Expression: MIT
License-File: LICENSE
Keywords: api-client,earth-observation,geospatial,imagery,remote-sensing,satellite,sdk,stac,thermal
Classifier: Development Status :: 4 - Beta
Classifier: Framework :: Pydantic :: 2
Classifier: Intended Audience :: Developers
Classifier: Intended Audience :: Science/Research
Classifier: License :: OSI Approved :: MIT License
Classifier: Operating System :: OS Independent
Classifier: Programming Language :: Python :: 3
Classifier: Programming Language :: Python :: 3 :: Only
Classifier: Programming Language :: Python :: 3.10
Classifier: Programming Language :: Python :: 3.11
Classifier: Programming Language :: Python :: 3.12
Classifier: Programming Language :: Python :: 3.13
Classifier: Topic :: Scientific/Engineering :: GIS
Classifier: Topic :: Scientific/Engineering :: Image Processing
Classifier: Topic :: Software Development :: Libraries :: Python Modules
Classifier: Typing :: Typed
Requires-Python: >=3.10
Requires-Dist: pydantic>=2.11.7
Provides-Extra: http-httpx
Requires-Dist: httpx>=0.28.1; extra == 'http-httpx'
Provides-Extra: http-requests
Requires-Dist: requests>=2.32.0; extra == 'http-requests'
Provides-Extra: http-urllib3
Requires-Dist: urllib3>=2.0.0; extra == 'http-urllib3'
Provides-Extra: standard
Requires-Dist: appdirs>=1.4.4; extra == 'standard'
